<?xml version="1.0" encoding="utf-8"?>
<!--

    Copyright (C) 2014 Xillio (support@xillio.com)

    Licensed under the Apache License, Version 2.0 (the "License");
    you may not use this file except in compliance with the License.
    You may obtain a copy of the License at

            http://www.apache.org/licenses/LICENSE-2.0

    Unless required by applicable law or agreed to in writing, software
    distributed under the License is distributed on an "AS IS" BASIS,
    WITHOUT WARRANTIES OR CONDITIONS OF ANY KIND, either express or implied.
    See the License for the specific language governing permissions and
    limitations under the License.

-->
<function>
    <description>
Determines if the file or folder at the given `path` is hidden.
    </description>
	<parameterDescriptions>
		<parameterDescription parameterName="path">
The path that will be checked. This can be either a file or a folder, relative or absolute.
        </parameterDescription>
	</parameterDescriptions>
	<longDescription>
Returns `true` if the path or folder is hidden or `false` otherwise.
	</longDescription>
    <examples>
        <example title="Usage">
            <header>Determine if the specified file or folder is hidden or not.</header>
            <code>
                use File;
                use System;
                use Stream;

                // We create a file that we can work with.
                var path = "TestFile.txt";
                var testFile = File.openWrite(path);
                Stream.write("test", testFile);

                System.print(File.isHidden(path));
                // This will print: false
            </code>
        </example>
    </examples>
    <references>
        <reference>canExecute</reference>
        <reference>canRead</reference>
        <reference>canWrite</reference>
        <reference>isFile</reference>
        <reference>isFolder</reference>
        <reference>isLink</reference>
    </references>
    <tags>
        read, write, execute, hidden
    </tags>
</function>